main.py
setup.py
ic_flow_platform.egg-info/PKG-INFO
ic_flow_platform.egg-info/SOURCES.txt
ic_flow_platform.egg-info/dependency_links.txt
ic_flow_platform.egg-info/requires.txt
ic_flow_platform.egg-info/top_level.txt